[1,["27a2JOjsVBSq5BunzSWTUq@6c48a"],["_textureSource"],["cc.SpriteFrame"],0,[{"name":"element_l","rect":{"x":24,"y":21,"width":234,"height":152},"offset":{"x":-9,"y":-7},"originalSize":{"width":300,"height":180},"rotated":false,"capInsets":[0,0,0,0],"vertices":{"rawPosition":[-117,-76,0,117,-76,0,-117,76,0,117,76,0],"indexes":[0,1,2,2,1,3],"uv":[24,159,258,159,24,7,258,7],"nuv":[0.08,0.03888888888888889,0.86,0.03888888888888889,0.08,0.8833333333333333,0.86,0.8833333333333333],"minPos":{"x":-117,"y":-76,"z":0},"maxPos":{"x":117,"y":76,"z":0}},"packable":true,"pixelsToUnit":100,"pivot":{"x":0.5,"y":0.5},"meshType":0}],[0],0,[0],[0],[0]]
