[1,["ecpdLyjvZBwrvm+cedCcQy","6e896FmWVGL516BSuGgCJ7","f5q7t9tBNAr60bVabT87Br","3cMz7fSItLU7SI8+N5Lg7D","d4dpLgA/RBJKyx10XU/GEl","b9lMW3SipEpYQD+O52JBSb","051aqjs6hI7LTz27R0Tu1V","86SdukvzVNn4H9IkUyL7Mt","cfVV/8lDZIDKVMaayFpxZk","cdjEbZLStHvZJFS8eOahyW","f0BIwQ8D5Ml7nTNQbh1YlS","29FYIk+N1GYaeWH/q1NxQO"],["node","_spriteFrame","_textureSetter","root","btnPrivacy","btnService","closeBtn","ctx","data","_parent","_N$file","_N$normalSprite","_N$disabledSprite"],[["cc.Node",["_name","_components","_prefab","_trs","_contentSize","_parent","_children","_color","_anchorPoint"],2,9,4,7,5,1,2,5,5],["cc.Label",["_string","_fontSize","_N$verticalAlign","_lineHeight","_N$horizontalAlign","_styleFlags","_isSystemFontUsed","_N$overflow","node","_materials","_N$file"],-5,1,3,6],"cc.SpriteFrame",["cc.Node",["_name","_parent","_components","_prefab","_contentSize","_trs","_children","_color"],2,1,2,4,5,7,2,5],["cc.Widget",["_alignFlags","alignMode","_left","_right","_top","_bottom","_originalWidth","_originalHeight","node"],-5,1],["cc.PrefabInfo",["fileId","root","asset"],2,1,1],["cc.Sprite",["_type","_sizeMode","node","_materials","_spriteFrame"],1,1,3,6],["cc.Prefab",["_name"],2],["a457crloztMaIIPhRnZ7Hh/",["node","ctx","closeBtn","btnService","btnPrivacy"],3,1,1,1,1,1],["cc.BlockInputEvents",["node"],3,1],["cc.Button",["zoomScale","_N$transition","node","clickEvents","_N$normalColor","_N$disabledColor","_N$target"],1,1,9,5,5,1],["cc.ClickEvent",["_componentId","handler","target"],1,1]],[[5,0,1,2,2],[6,0,1,2,3,4,3],[0,0,5,1,2,4,3,2],[0,0,5,1,2,7,4,3,2],[3,0,1,2,3,7,4,5,2],[1,0,1,5,4,2,8,9,6],[7,0,2],[0,0,6,1,2,3,2],[0,0,6,1,2,4,3,2],[0,0,5,6,1,2,4,3,2],[0,0,5,1,2,4,8,3,2],[3,0,1,6,2,3,4,5,2],[4,0,8,2],[4,1,0,2,3,4,5,6,7,8,9],[8,0,1,2,3,4,1],[5,1,2,1],[6,2,3,4,1],[9,0,1],[1,0,1,3,6,4,2,8,9,10,7],[1,0,1,3,5,2,7,8,9,7],[10,0,1,2,3,4,5,6,3],[11,0,1,2,3]],[[[{"name":"rw_btn3","rect":[0,0,171,71],"offset":[0,0],"originalSize":[171,71],"capInsets":[0,0,0,0]}],[2],0,[0],[2],[1]],[[{"name":"yinsi_1","rect":[0,0,81,42],"offset":[0,0],"originalSize":[81,42],"capInsets":[0,0,0,0]}],[2],0,[0],[2],[2]],[[[6,"ui_privacy"],[7,"ui_privacy",[-8,-9,-10,-11,-12,-13,-14,-15],[[12,18,-2],[14,-7,-6,-5,-4,-3]],[15,-1,0],[360,640,0,0,0,0,1,1,1,1]],[8,"bg",[-18],[[1,1,0,-16,[15],16],[13,0,45,2,-2,1,-1,100,40,-17]],[0,"02toErpw1ILYeeQA1zD6Ca",1,0],[5,252,86],[2,-1,0,0,0,0,1,1,1,0]],[2,"bg",1,[[1,1,0,-19,[0],1],[17,-20]],[0,"6bLS6VPw5Gp6yL+jSq0Rb6",1,0],[5,634,580],[0,56,0,0,0,0,1,1,1,1]],[9,"img_tc_bt",1,[-22],[[1,1,0,-21,[4],5]],[0,"7531KDkz5Ol5fXUoeWVEs5",1,0],[5,400,45],[0,310,0,0,0,0,1,1,1,1]],[11,"get",1,[2],[-23],[0,"54yzHgGBpHv4q/fmyOZ4SK",1,0],[5,252,86],[0,-152,0,0,0,0,1,1,1,1]],[3,"title",4,[[18,"用户隐私保护协议",50,50,false,1,1,-24,[2],3]],[0,"5eWMhim4dLVbH3+f2V1m0F",1,0],[4,4289260283],[5,277.78,50],[0,2,0,0,0,0,1,1,1,1]],[10,"bg0",1,[[1,1,0,-25,[6],7]],[0,"0apv81j49FWaYbbPt0B5W9",1,0],[5,589,480],[0,0.5,1],[0,262,0,0,0,0,1,1,1,1]],[2,"bg1",1,[[1,1,0,-26,[8],9]],[0,"5e4qspNV5Kjot+dc5lU2lQ",1,0],[5,560,323],[0,84,0,0,0,0,1,1,1,1]],[3,"info",1,[[19,"      欢迎来到每天数独，我们非常重视您的个人信息保护，在您进入游戏前，请您阅读并同意我们的用户协议、隐私政策。\n      您可以在设置内再次查看相关协议!",28,48,1,1,3,-27,[10]]],[0,"f6XU/VIs5Abqp7N0k5BKYw",1,0],[4,4280243878],[5,520,204.48],[-2,121.298,0,0,0,0,1,1,1,1]],[4,"btn_service",1,[-28],[0,"cdLpY58P5J5ZGL5LgQaecR",1,0],[4,4279989796],[5,186,50.4],[-93,-32,0,0,0,0,1,1,1,1]],[5,"《用户协议》",31,1,1,1,10,[11]],[4,"btn_privacy",1,[-29],[0,"c3Lj0586dJv4pk17aHUR22",1,0],[4,4279989796],[5,186,50.4],[89,-32,0,0,0,0,1,1,1,1]],[5,"《隐私政策》",31,1,1,1,12,[12]],[2,"New Sprite",2,[[16,-30,[13],14]],[0,"31phgQYBlODbLGyp0Yeu0x",1,0],[5,81,42],[-6,6,0,0,0,0,1,1,1,1]],[20,0.9,3,5,[[21,"c5238cXPXJEF72dKgiQwbZ5","onGet",1]],[4,4293322470],[4,3363338360],2]],0,[0,3,1,0,0,1,0,4,13,0,5,11,0,6,15,0,7,1,0,0,1,0,-1,3,0,-2,4,0,-3,7,0,-4,8,0,-5,9,0,-6,10,0,-7,12,0,-8,5,0,0,2,0,0,2,0,-1,14,0,0,3,0,0,3,0,0,4,0,-1,6,0,-1,15,0,0,6,0,0,7,0,0,8,0,0,9,0,-1,11,0,-1,13,0,0,14,0,8,1,2,9,5,30],[0,0,0,0,0,0,0,0,0,0,0,0,0,0,0,0,0,15,15],[-1,1,-1,10,-1,1,-1,1,-1,1,-1,-1,-1,-1,1,-1,1,11,12],[0,3,0,4,0,5,0,6,0,7,0,0,0,0,8,0,9,10,11]]]]